{
  "fields": "[{\"name\":\"gid\",\"type\":\"string\",\"count\":0,\"scripted\":false,\"indexed\":true,\"analyzed\":true,\"doc_values\":false},{\"name\":\"_index\",\"type\":\"string\",\"count\":0,\"scripted\":false,\"indexed\":false,\"analyzed\":false,\"doc_values\":false},{\"name\":\"description.raw\",\"type\":\"string\",\"count\":0,\"scripted\":false,\"indexed\":true,\"analyzed\":false,\"doc_values\":true},{\"name\":\"description\",\"type\":\"string\",\"count\":0,\"scripted\":false,\"indexed\":true,\"analyzed\":true,\"doc_values\":false},{\"name\":\"type\",\"type\":\"string\",\"count\":0,\"scripted\":false,\"indexed\":true,\"analyzed\":true,\"doc_values\":false},{\"name\":\"tab\",\"type\":\"string\",\"count\":0,\"scripted\":false,\"indexed\":true,\"analyzed\":true,\"doc_values\":false},{\"name\":\"@version\",\"type\":\"string\",\"count\":0,\"scripted\":false,\"indexed\":true,\"analyzed\":false,\"doc_values\":true},{\"name\":\"gid.raw\",\"type\":\"string\",\"count\":0,\"scripted\":false,\"indexed\":true,\"analyzed\":false,\"doc_values\":true},{\"name\":\"tab.raw\",\"type\":\"string\",\"count\":0,\"scripted\":false,\"indexed\":true,\"analyzed\":false,\"doc_values\":true},{\"name\":\"value\",\"type\":\"number\",\"count\":0,\"scripted\":false,\"indexed\":true,\"analyzed\":false,\"doc_values\":true},{\"name\":\"info\",\"type\":\"string\",\"count\":0,\"scripted\":false,\"indexed\":true,\"analyzed\":true,\"doc_values\":false},{\"name\":\"group\",\"type\":\"string\",\"count\":0,\"scripted\":false,\"indexed\":true,\"analyzed\":true,\"doc_values\":false},{\"name\":\"xgroup\",\"type\":\"string\",\"count\":0,\"scripted\":false,\"indexed\":true,\"analyzed\":true,\"doc_values\":false},{\"name\":\"info.raw\",\"type\":\"string\",\"count\":0,\"scripted\":false,\"indexed\":true,\"analyzed\":false,\"doc_values\":true},{\"name\":\"ip\",\"type\":\"ip\",\"count\":0,\"scripted\":false,\"indexed\":true,\"analyzed\":false,\"doc_values\":true},{\"name\":\"type.raw\",\"type\":\"string\",\"count\":0,\"scripted\":false,\"indexed\":true,\"analyzed\":false,\"doc_values\":true},{\"name\":\"@timestamp\",\"type\":\"date\",\"count\":0,\"scripted\":false,\"indexed\":true,\"analyzed\":false,\"doc_values\":true},{\"name\":\"group.raw\",\"type\":\"string\",\"count\":0,\"scripted\":false,\"indexed\":true,\"analyzed\":false,\"doc_values\":true},{\"name\":\"xgroup.raw\",\"type\":\"string\",\"count\":0,\"scripted\":false,\"indexed\":true,\"analyzed\":false,\"doc_values\":true},{\"name\":\"_source\",\"type\":\"_source\",\"count\":0,\"scripted\":false,\"indexed\":false,\"analyzed\":false,\"doc_values\":false},{\"name\":\"ts\",\"type\":\"date\",\"count\":0,\"scripted\":false,\"indexed\":true,\"analyzed\":false,\"doc_values\":true},{\"name\":\"tag.raw\",\"type\":\"string\",\"count\":0,\"scripted\":false,\"indexed\":true,\"analyzed\":false,\"doc_values\":true},{\"name\":\"tag\",\"type\":\"string\",\"count\":0,\"scripted\":false,\"indexed\":true,\"analyzed\":true,\"doc_values\":false},{\"name\":\"reply\",\"type\":\"string\",\"count\":0,\"scripted\":false,\"indexed\":true,\"analyzed\":true,\"doc_values\":false},{\"name\":\"reply.raw\",\"type\":\"string\",\"count\":0,\"scripted\":false,\"indexed\":true,\"analyzed\":false,\"doc_values\":true},{\"name\":\"cseq\",\"type\":\"string\",\"count\":0,\"scripted\":false,\"indexed\":true,\"analyzed\":true,\"doc_values\":false},{\"name\":\"cseq.raw\",\"type\":\"string\",\"count\":0,\"scripted\":false,\"indexed\":true,\"analyzed\":false,\"doc_values\":true},{\"name\":\"method.raw\",\"type\":\"string\",\"count\":0,\"scripted\":false,\"indexed\":true,\"analyzed\":false,\"doc_values\":true},{\"name\":\"method\",\"type\":\"string\",\"count\":0,\"scripted\":false,\"indexed\":true,\"analyzed\":true,\"doc_values\":false},{\"name\":\"uac\",\"type\":\"string\",\"count\":0,\"scripted\":false,\"indexed\":true,\"analyzed\":true,\"doc_values\":false},{\"name\":\"uac.raw\",\"type\":\"string\",\"count\":0,\"scripted\":false,\"indexed\":true,\"analyzed\":false,\"doc_values\":true},{\"name\":\"metaobj.domain\",\"type\":\"string\",\"count\":0,\"scripted\":false,\"indexed\":true,\"analyzed\":true,\"doc_values\":false},{\"name\":\"metaobj.user.raw\",\"type\":\"string\",\"count\":0,\"scripted\":false,\"indexed\":true,\"analyzed\":false,\"doc_values\":true},{\"name\":\"metaobj.name\",\"type\":\"string\",\"count\":0,\"scripted\":false,\"indexed\":true,\"analyzed\":true,\"doc_values\":false},{\"name\":\"metaobj.name.raw\",\"type\":\"string\",\"count\":0,\"scripted\":false,\"indexed\":true,\"analyzed\":false,\"doc_values\":true},{\"name\":\"metaobj.user\",\"type\":\"string\",\"count\":0,\"scripted\":false,\"indexed\":true,\"analyzed\":true,\"doc_values\":false},{\"name\":\"metaobj.description.raw\",\"type\":\"string\",\"count\":0,\"scripted\":false,\"indexed\":true,\"analyzed\":false,\"doc_values\":true},{\"name\":\"metaobj.description\",\"type\":\"string\",\"count\":0,\"scripted\":false,\"indexed\":true,\"analyzed\":true,\"doc_values\":false},{\"name\":\"metaobj.domain.raw\",\"type\":\"string\",\"count\":0,\"scripted\":false,\"indexed\":true,\"analyzed\":false,\"doc_values\":true},{\"name\":\"_id\",\"type\":\"string\",\"count\":0,\"scripted\":false,\"indexed\":false,\"analyzed\":false,\"doc_values\":false},{\"name\":\"_type\",\"type\":\"string\",\"count\":0,\"scripted\":false,\"indexed\":false,\"analyzed\":false,\"doc_values\":false},{\"name\":\"_score\",\"type\":\"number\",\"count\":0,\"scripted\":false,\"indexed\":false,\"analyzed\":false,\"doc_values\":false}]", 
  "timeFieldName": "@timestamp", 
  "title": "pcapture_gid*-*"
}